accessible_output2/__init__.py
accessible_output2/lib/PCTKUSR.dll
accessible_output2/lib/PCTKUSR64.dll
accessible_output2/lib/SAAPI32.dll
accessible_output2/lib/ZDSRAPI.dll
accessible_output2/lib/ZDSRAPI_x64.dll
accessible_output2/lib/dolapi.dll
accessible_output2/lib/nvdaControllerClient32.dll
accessible_output2/lib/nvdaControllerClient64.dll
accessible_output2/outputs/__init__.py
accessible_output2/outputs/auto.py
accessible_output2/outputs/base.py
accessible_output2/outputs/dolphin.py
accessible_output2/outputs/e_speak.py
accessible_output2/outputs/jaws.py
accessible_output2/outputs/nvda.py
accessible_output2/outputs/pc_talker.py
accessible_output2/outputs/sapi4.py
accessible_output2/outputs/sapi5.py
accessible_output2/outputs/speech_dispatcher.py
accessible_output2/outputs/system_access.py
accessible_output2/outputs/voiceover.py
accessible_output2/outputs/window_eyes.py
accessible_output2/outputs/zdsr.py
accessible_output2-0.17.dist-info/LICENSE
accessible_output2-0.17.dist-info/METADATA
accessible_output2-0.17.dist-info/WHEEL
accessible_output2-0.17.dist-info/top_level.txt
accessible_output2-0.17.dist-info/RECORD
