Metadata-Version: 1.1
Name: accessible-output2
Version: 0.17
Summary: Library to provide speech and braille output to a variety of different screen readers and other accessibility solutions.
Home-page: UNKNOWN
Author: Tyler Spivey
Author-email: tspivey@pcdesk.net
License: UNKNOWN
Platform: UNKNOWN
Classifier: Development Status :: 5 - Production/Stable
Classifier: Intended Audience :: Developers
Classifier: Operating System :: Microsoft :: Windows
Classifier: Programming Language :: Python
Classifier: License :: OSI Approved :: MIT License
Classifier: Topic :: Adaptive Technologies
Classifier: Topic :: Software Development :: Libraries
